LICENSE
MANIFEST.in
README.md
setup.cfg
setup.py
django_baseurl/__init__.py
django_baseurl/context_processors.py
django_baseurl.egg-info/PKG-INFO
django_baseurl.egg-info/SOURCES.txt
django_baseurl.egg-info/dependency_links.txt
django_baseurl.egg-info/top_level.txt